claude_config_sync/__init__.py
claude_config_sync/__main__.py
claude_config_sync/config_manager.py
claude_config_sync/path_resolver.py
claude_config_sync/remote_fetcher.py
claude_config_sync/server.py
claude_config_sync-2.1.1.dist-info/METADATA
claude_config_sync-2.1.1.dist-info/WHEEL
claude_config_sync-2.1.1.dist-info/entry_points.txt
claude_config_sync-2.1.1.dist-info/RECORD
