Metadata-Version: 2.4
Name: claude-config-sync
Version: 2.1.1
Summary: MCP server for syncing Claude Desktop config with remote Digital Ocean config
Project-URL: Homepage, https://github.com/example/claude-config-sync
Project-URL: Repository, https://github.com/example/claude-config-sync
Author-email: Claude Config Sync <support@example.com>
License: MIT
Keywords: claude,config,digitalocean,mcp,sync
Classifier: Development Status :: 3 - Alpha
Classifier: Intended Audience :: Developers
Classifier: License :: OSI Approved :: MIT License
Classifier: Programming Language :: Python :: 3
Classifier: Programming Language :: Python :: 3.8
Classifier: Programming Language :: Python :: 3.9
Classifier: Programming Language :: Python :: 3.10
Classifier: Programming Language :: Python :: 3.11
Classifier: Programming Language :: Python :: 3.12
Requires-Python: >=3.10
Requires-Dist: anyio>=3.0.0
Requires-Dist: boto3>=1.26.0
Requires-Dist: mcp>=1.0.0
Requires-Dist: requests>=2.25.0
